LICENSE
MANIFEST.in
README.md
pyproject.toml
setup.py
version.txt
assist/__init__.py
assist/ephem.py
assist/extras.py
assist/py.typed
assist/tools.py
assist.egg-info/PKG-INFO
assist.egg-info/SOURCES.txt
assist.egg-info/dependency_links.txt
assist.egg-info/not-zip-safe
assist.egg-info/requires.txt
assist.egg-info/top_level.txt
src/assist.c
src/assist.h
src/forces.c
src/forces.h
src/planets.c
src/planets.h
src/spk.c
src/spk.h
src/tools.c
src/tools.h