Metadata-Version: 2.1
Name: assist
Version: 1.1.10
Summary: A library high accuracy ephemeris in REBOUND
Home-page: https://github.com/matthewholman/assist
Author: Matthew Holman
Author-email: mholman@cfa.harvard.edu
License: GPL
Keywords: astronomy astrophysics nbody integrator
Classifier: Development Status :: 5 - Production/Stable
Classifier: Intended Audience :: Science/Research
Classifier: Intended Audience :: Developers
Classifier: Topic :: Software Development :: Build Tools
Classifier: Topic :: Scientific/Engineering :: Astronomy
Classifier: License :: OSI Approved :: GNU General Public License v3 or later (GPLv3+)
Classifier: Programming Language :: Python :: 3
License-File: LICENSE
